{"download": 888080386.5614643, "upload": 915248003.3368405, "ping": 1.249, "server": {"url": "http://speedtest.jztkft.hu:8080/speedtest/upload.php", "lat": "47.4979", "lon": "19.0402", "name": "Budapest", "country": "Hungary", "cc": "HU", "sponsor": "JZT Informatikai Kft", "id": "24446", "host": "speedtest.jztkft.hu:8080", "d": 8.373346501527532, "latency": 1.249}, "timestamp": "2021-01-28T21:06:04.222724Z", "bytes_sent": 151519232, "bytes_received": 409373932, "share": null, "client": {"ip": "193.224.4.20", "lat": "47.5636", "lon": "19.0947", "isp": "KIFU (Governmental Info Tech Development Agency)", "isprating": "3.7", "rating": "0", "ispdlavg": "0", "ispulavg": "0", "loggedin": "0", "country": "HU"}}
