{"download": 938945470.0970914, "upload": 897491250.6983594, "ping": 1.926, "server": {"url": "http://speedtest.ahrt.hu:8080/speedtest/upload.php", "lat": "47.5000", "lon": "19.0500", "name": "Budapest", "country": "Hungary", "cc": "HU", "sponsor": "Antenna Hung\u00e1ria Zrt.", "id": "12374", "host": "speedtest.ahrt.hu:8080", "d": 7.827860119074034, "latency": 1.926}, "timestamp": "2021-02-14T06:11:03.022248Z", "bytes_sent": 151519232, "bytes_received": 409373932, "share": null, "client": {"ip": "193.224.4.20", "lat": "47.5636", "lon": "19.0947", "isp": "KIFU (Governmental Info Tech Development Agency)", "isprating": "3.7", "rating": "0", "ispdlavg": "0", "ispulavg": "0", "loggedin": "0", "country": "HU"}}
