{"download": 613213806.9827452, "upload": 706912279.3001769, "ping": 10.0, "server": {"url": "http://speedtest02.timewarp.at:8080/speedtest/upload.php", "lat": "48.2082", "lon": "16.3738", "name": "Vienna", "country": "Austria", "cc": "AT", "sponsor": "Timewarp IT Consulting GmbH", "id": "15819", "host": "speedtest02.timewarp.at:8080", "d": 215.16683585786217, "latency": 10.0}, "timestamp": "2021-01-28T03:58:03.844120Z", "bytes_sent": 151519232, "bytes_received": 409373932, "share": null, "client": {"ip": "193.224.4.20", "lat": "47.5636", "lon": "19.0947", "isp": "KIFU (Governmental Info Tech Development Agency)", "isprating": "3.7", "rating": "0", "ispdlavg": "0", "ispulavg": "0", "loggedin": "0", "country": "HU"}}
