{"download": 665966978.3094267, "upload": 456371830.9819212, "ping": 14.091, "server": {"url": "http://speedtest.cis.vutbr.cz:8080/speedtest/upload.php", "lat": "49.1953", "lon": "16.6083", "name": "Brno", "country": "Czech Republic", "cc": "CZ", "sponsor": "Brno University of Technology", "id": "4468", "host": "speedtest.cis.vutbr.cz:8080", "d": 260.5654102837363, "latency": 14.091}, "timestamp": "2020-11-24T18:45:04.375622Z", "bytes_sent": 151519232, "bytes_received": 409373932, "share": null, "client": {"ip": "157.181.46.136", "lat": "47.4984", "lon": "19.0404", "isp": "Eltenet Eltenet", "isprating": "3.7", "rating": "0", "ispdlavg": "0", "ispulavg": "0", "loggedin": "0", "country": "HU"}}
