{"download": 905872674.1725627, "upload": 880777836.4527259, "ping": 3.522, "server": {"url": "http://gyor-speedtest.zt.hu:8080/speedtest/upload.php", "lat": "47.6875", "lon": "17.6504", "name": "Gyor", "country": "Hungary", "cc": "HU", "sponsor": "ZNET Telekom Zrt.", "id": "9720", "host": "gyor-speedtest.zt.hu:8080", "d": 106.33298241453866, "latency": 3.522}, "timestamp": "2020-11-25T01:18:03.405325Z", "bytes_sent": 151519232, "bytes_received": 409373932, "share": null, "client": {"ip": "157.181.46.136", "lat": "47.4984", "lon": "19.0404", "isp": "Eltenet Eltenet", "isprating": "3.7", "rating": "0", "ispdlavg": "0", "ispulavg": "0", "loggedin": "0", "country": "HU"}}
