{"download": 936154799.5595391, "upload": 883055037.1431813, "ping": 1.326, "server": {"url": "http://speedtest.ahrt.hu:8080/speedtest/upload.php", "lat": "47.5000", "lon": "19.0500", "name": "Budapest", "country": "Hungary", "cc": "HU", "sponsor": "Antenna Hung\u00e1ria Zrt.", "id": "12374", "host": "speedtest.ahrt.hu:8080", "d": 0.6610753911297887, "latency": 1.326}, "timestamp": "2021-01-13T00:28:03.339609Z", "bytes_sent": 151519232, "bytes_received": 409373932, "share": null, "client": {"ip": "193.224.4.20", "lat": "47.5", "lon": "19.0412", "isp": "KIFU (Governmental Info Tech Development Agency)", "isprating": "3.7", "rating": "0", "ispdlavg": "0", "ispulavg": "0", "loggedin": "0", "country": "HU"}}
