{"download": 876060509.7426863, "upload": 715948413.8018104, "ping": 13.005, "server": {"url": "http://saskia.net-connect.cz:8080/speedtest/upload.php", "lat": "48.8529", "lon": "17.1260", "name": "Hodon\u00edn", "country": "Czechia", "cc": "CZ", "sponsor": "Net-connect s.r.o.", "id": "38785", "host": "saskia.net-connect.cz:8080", "d": 204.52539982837476, "latency": 13.005}, "timestamp": "2021-01-27T22:08:03.529004Z", "bytes_sent": 151519232, "bytes_received": 409373932, "share": null, "client": {"ip": "193.224.4.20", "lat": "47.5636", "lon": "19.0947", "isp": "KIFU (Governmental Info Tech Development Agency)", "isprating": "3.7", "rating": "0", "ispdlavg": "0", "ispulavg": "0", "loggedin": "0", "country": "HU"}}
