{"download": 924055407.8305733, "upload": 893420111.8659102, "ping": 1.803, "server": {"url": "http://speedtest.hostingbazis.hu:8080/speedtest/upload.php", "lat": "47.4979", "lon": "19.0402", "name": "Budapest", "country": "Hungary", "cc": "HU", "sponsor": "HostingBazis Bt.", "id": "26895", "host": "speedtest.hostingbazis.hu:8080", "d": 0.05759190615836983, "latency": 1.803}, "timestamp": "2020-11-24T05:17:02.759118Z", "bytes_sent": 151519232, "bytes_received": 409373932, "share": null, "client": {"ip": "157.181.46.136", "lat": "47.4984", "lon": "19.0404", "isp": "Eltenet Eltenet", "isprating": "3.7", "rating": "0", "ispdlavg": "0", "ispulavg": "0", "loggedin": "0", "country": "HU"}}
